apis_highlighter/__init__.py
apis_highlighter/admin.py
apis_highlighter/apps.py
apis_highlighter/helpers.py
apis_highlighter/models.py
apis_highlighter/signals.py
apis_highlighter/urls.py
apis_highlighter/views.py
apis_highlighter/migrations/0001_initial.py
apis_highlighter/migrations/0002_rename_annotation_project_annotation_project_and_more.py
apis_highlighter/migrations/0003_annotation_text_field_name.py
apis_highlighter/migrations/__init__.py
apis_highlighter/static/css/highlighter.css
apis_highlighter/static/js/highlighter.js
apis_highlighter/templates/apis_highlighter/annotation_confirm_delete.html
apis_highlighter/templates/apis_highlighter/apis_highlighter.html
apis_highlighter/templates/apis_highlighter/select_project.html
apis_highlighter/templatetags/apis_highlighter.py
apis_highlighter_ng-0.6.3.dist-info/METADATA
apis_highlighter_ng-0.6.3.dist-info/WHEEL
apis_highlighter_ng-0.6.3.dist-info/licenses/LICENSE
apis_highlighter_ng-0.6.3.dist-info/RECORD
