Metadata-Version: 2.4
Name: apis-highlighter-ng
Version: 0.6.3
Summary: Highlighter for the APIS project
Project-URL: source, https://github.com/acdh-oeaw/apis-highlighter-ng
Project-URL: changelog, https://github.com/acdh-oeaw/apis-highlighter-ng/blob/main/CHANGELOG.md
Project-URL: issues, https://github.com/acdh-oeaw/apis-highlighter-ng/issues
Author-email: Birger Schacht <birger.schacht@oeaw.ac.at>
License-Expression: MIT
License-File: LICENSE
Requires-Python: >=3.11
Requires-Dist: apis-core-rdf>=0.29.0
Requires-Dist: django>=4.1
